pyged/__init__.py
pyged/import.py
pyged/mkgraph.py
pyged/mkline.py
pyged/mkreport.py
pyged/mktexline.py
pyged/gedcom/__init__.py
pyged/gedcom/date.py
pyged/gedcom/edit.py
pyged/gedcom/errors.py
pyged/gedcom/events.py
pyged/gedcom/gedcom.py
pyged/gedcom/matches.py
pyged/gedcom/media.py
pyged/gedcom/mkrecords.py
pyged/gedcom/notes.py
pyged/gedcom/place.py
pyged/gedcom/records.py
pyged/report/__init__.py
pyged/report/aux.py
pyged/report/bibtex.py
pyged/report/date.py
pyged/report/directline.py
pyged/report/graph.py
pyged/report/report.py
pyged/report/tex.py
pyged-0.2.1.dist-info/METADATA
pyged-0.2.1.dist-info/WHEEL
pyged-0.2.1.dist-info/licenses/LICENSE.txt
pyged-0.2.1.dist-info/RECORD
