Metadata-Version: 2.4
Name: pyged
Version: 0.2.1
Summary: A simple Python GEDCOM parser
Project-URL: Homepage, https://github.com/hgeorgsch/pyged
Project-URL: Issues, https://github.com/hgeorgsch/pyged/issues
Author-email: Hans Georg Schaathun <georg+github@schaathun.net>
License-Expression: GPL-3.0
License-File: LICENSE.txt
Keywords: gedcom,genealogy
Classifier: Development Status :: 4 - Beta
Classifier: Intended Audience :: Developers
Classifier: Operating System :: OS Independent
Classifier: Programming Language :: Python :: 3
Classifier: Topic :: Sociology :: Genealogy
Classifier: Topic :: Software Development :: Libraries :: Python Modules
Requires-Python: >=3.11
